MANIFEST.in
README
__init__.py
__pkginfo__.py
authplugin.py
entities.py
hooks.py
schema.py
setup.py
uiprops.py
utils.py
views.py
cubicweb_openidrelay.egg-info/PKG-INFO
cubicweb_openidrelay.egg-info/SOURCES.txt
cubicweb_openidrelay.egg-info/dependency_links.txt
cubicweb_openidrelay.egg-info/requires.txt
cubicweb_openidrelay.egg-info/top_level.txt
data/cubes.openidrelay.js
data/openid-16x16.gif
i18n/en.po
i18n/es.po
i18n/fr.po
migration/postcreate.py
test/pytestconf.py
test/test_openidrelay.py