Metadata-Version: 1.0
Name: cubicweb-openidrelay
Version: 0.1.2
Summary: An authentication plugin to turn a cubicweb instance into an OpenID relay.
Home-page: http://www.cubicweb.org/project/cubicweb-openidrelay
Author: LOGILAB S.A. (Paris, FRANCE)
Author-email: contact@logilab.fr
License: LGPL
Platform: UNKNOWN
